swarm_bus/__init__.py
swarm_bus/bus.py
swarm_bus/connector.py
swarm_bus/constants.py
swarm_bus/consumer.py
swarm_bus/deleter.py
swarm_bus/lister.py
swarm_bus/publisher.py
swarm_bus/purger.py
swarm_bus/queue.py
swarm_bus/transport.py
swarm_bus-5.18.dist-info/METADATA
swarm_bus-5.18.dist-info/WHEEL
swarm_bus-5.18.dist-info/top_level.txt
swarm_bus-5.18.dist-info/RECORD
