Metadata-Version: 2.1
Name: swarm-bus
Version: 5.18
Summary: ESB SQS based
Home-page: https://bitbucket.org/monalgroup/swarm-bus
Author: The Swarm Team
Author-email: dev@hiventy.com
License: GPL License
Keywords: ESB,tools,swarm,bus
Platform: UNKNOWN
Classifier: Intended Audience :: Developers
Classifier: Operating System :: OS Independent
Classifier: Topic :: Software Development
Classifier: Programming Language :: Python
Classifier: Programming Language :: Python :: 3
Requires-Dist: boto3 (>=1.14.20)
Requires-Dist: python-slugify (==4.0.1)
